VisionCraft/__init__.py
VisionCraft/craft/__init__.py
VisionCraft/help/__init__.py
VisionCraft/help/exp.py
VisionCraft/help/Experiment/__init__.py
VisionCraft/vision/__init__.py
VisionCraft/vision/filter.py
VisionCraft/vision/huffman.py
VisionCraft/vision/processing.py
VisionCraft/vision/segmentation.py
VisionCraft/vision/transform.py
VisionCraft/vision/utils.py
VisionCraft-0.1.27.dist-info/LICENSE
VisionCraft-0.1.27.dist-info/METADATA
VisionCraft-0.1.27.dist-info/WHEEL
VisionCraft-0.1.27.dist-info/top_level.txt
VisionCraft-0.1.27.dist-info/RECORD
