Metadata-Version: 2.1
Name: VisionCraft
Version: 0.1.27
Summary: Computer Vision Library to help do CV much faster, Updated Filters
Author: Prem Gaikwad
Author-email: premgaikwad7a@gmail.com
Keywords: python,CNN,cv
Classifier: Development Status :: 1 - Planning
Classifier: Intended Audience :: Developers
Classifier: Programming Language :: Python :: 3
Classifier: Operating System :: Unix
Classifier: Operating System :: MacOS :: MacOS X
Classifier: Operating System :: Microsoft :: Windows
License-File: LICENSE
Requires-Dist: opencv-python
Requires-Dist: numpy
Requires-Dist: pandas
Requires-Dist: matplotlib
